[1,["c9DaNq+tBCwJBKPmDIoHGQ"],["_textureSetter"],["cc.SpriteFrame"],0,[[[{"name":"com-bg_frame","rect":[251,915,47,42],"offset":[0,0],"originalSize":[47,42],"rotated":1,"capInsets":[18,17,19,17]}],[0],0,[0],[0],[0]],[[{"name":"com-bg_inner","rect":[249,964,58,44],"offset":[0,0],"originalSize":[58,44],"rotated":1,"capInsets":[16,16,16,16]}],[0],0,[0],[0],[0]],[[{"name":"com-headline","rect":[971,56,86,51],"offset":[0,0],"originalSize":[86,51],"rotated":1,"capInsets":[20,0,19,0]}],[0],0,[0],[0],[0]]]]