[1,["14aE0iblhNmqDi8AhddQQ/"],["_textureSetter"],["cc.SpriteFrame"],0,[[[{"name":"actors-t_godfingertip-godFingerTip_2","rect":[1729,416,11,25],"offset":[0,0],"originalSize":[11,25],"capInsets":[0,0,0,0]}],[0],0,[0],[0],[0]],[[{"name":"actors-t_godfinger-godFinger_1","rect":[1175,895,23,23],"offset":[0,0],"originalSize":[23,23],"capInsets":[0,0,0,0]}],[0],0,[0],[0],[0]],[[{"name":"actors-t_godfinger-godFinger_0","rect":[1175,869,23,23],"offset":[0,0],"originalSize":[23,23],"capInsets":[0,0,0,0]}],[0],0,[0],[0],[0]],[[{"name":"actors-t_godfingertip-godFingerTip_0","rect":[1808,241,11,25],"offset":[0,0],"originalSize":[11,25],"capInsets":[0,0,0,0]}],[0],0,[0],[0],[0]],[[{"name":"actors-t_godfinger-godFinger_3","rect":[988,862,23,23],"offset":[0,0],"originalSize":[23,23],"capInsets":[0,0,0,0]}],[0],0,[0],[0],[0]],[[{"name":"actors-t_godfingertip-godFingerTip_4","rect":[780,648,11,25],"offset":[0,0],"originalSize":[11,25],"capInsets":[0,0,0,0]}],[0],0,[0],[0],[0]],[[{"name":"actors-t_godfingertip-godFingerTip_3","rect":[780,620,11,25],"offset":[0,0],"originalSize":[11,25],"capInsets":[0,0,0,0]}],[0],0,[0],[0],[0]],[[{"name":"actors-t_godfinger-godFinger_2","rect":[1037,850,23,23],"offset":[0,0],"originalSize":[23,23],"capInsets":[0,0,0,0]}],[0],0,[0],[0],[0]],[[{"name":"actors-t_godfingertip-godFingerTip_1","rect":[1729,388,11,25],"offset":[0,0],"originalSize":[11,25],"capInsets":[0,0,0,0]}],[0],0,[0],[0],[0]]]]